twitter.common.dirutil-0.3.10-py2.7-nspkg.pth
twitter/common/dirutil/__init__.py
twitter/common/dirutil/chroot.py
twitter/common/dirutil/fileset.py
twitter/common/dirutil/lock.py
twitter/common/dirutil/tail.py
twitter.common.dirutil-0.3.10.dist-info/DESCRIPTION.rst
twitter.common.dirutil-0.3.10.dist-info/METADATA
twitter.common.dirutil-0.3.10.dist-info/RECORD
twitter.common.dirutil-0.3.10.dist-info/WHEEL
twitter.common.dirutil-0.3.10.dist-info/metadata.json
twitter.common.dirutil-0.3.10.dist-info/namespace_packages.txt
twitter.common.dirutil-0.3.10.dist-info/top_level.txt
twitter.common.dirutil-0.3.10.dist-info/zip-safe
